lockhart/__about__.py
lockhart/__init__.py
lockhart/__main__.py
lockhart/config.py
lockhart/console.py
lockhart/history.py
lockhart/jinja_env.py
lockhart/prompts.py
lockhart/sample-lockhart.toml
lockhart/cli/__init__.py
lockhart/cli/common.py
lockhart/cli/config.py
lockhart/cli/history.py
lockhart/cli/prompt.py
lockhart/cli/tui.py
lockhart/tui/app.css
lockhart/tui/app.py
lockhart-0.6.2.dist-info/METADATA
lockhart-0.6.2.dist-info/WHEEL
lockhart-0.6.2.dist-info/entry_points.txt
lockhart-0.6.2.dist-info/licenses/LICENSE.txt
lockhart-0.6.2.dist-info/RECORD
