Metadata-Version: 2.1
Name: lockhart
Version: 0.6.2
Summary: generate docstrings
Project-URL: Documentation, https://github.com/waylonwalker/lockhart#readme
Project-URL: Issues, https://github.com/waylonwalker/lockhart/issues
Project-URL: Source, https://github.com/walker/lockhart
Author-email: "Waylon S. Walker" <waylon@waylonwalker.com>
License-Expression: MIT
License-File: LICENSE.txt
Classifier: Development Status :: 4 - Beta
Classifier: Programming Language :: Python
Classifier: Programming Language :: Python :: 3.7
Classifier: Programming Language :: Python :: 3.8
Classifier: Programming Language :: Python :: 3.9
Classifier: Programming Language :: Python :: 3.10
Classifier: Programming Language :: Python :: 3.11
Classifier: Programming Language :: Python :: Implementation :: CPython
Classifier: Programming Language :: Python :: Implementation :: PyPy
Requires-Python: >=3.7
Requires-Dist: jinja2
Requires-Dist: openai
Requires-Dist: pluggy
Requires-Dist: pyperclip
Requires-Dist: rich
Requires-Dist: textual
Requires-Dist: toml
Requires-Dist: tomlkit
Requires-Dist: typer
